setup.cfg
setup.py
hug_yaml/__init__.py
hug_yaml/_version.py
hug_yaml/input_format.py
hug_yaml/not_found.py
hug_yaml/output_format.py
hug_yaml.egg-info/PKG-INFO
hug_yaml.egg-info/SOURCES.txt
hug_yaml.egg-info/dependency_links.txt
hug_yaml.egg-info/requires.txt
hug_yaml.egg-info/top_level.txt